dubhub/__init__.py
dubhub/build_config.py
dubhub/client.py
dubhub/conftest.py
dubhub/tailscale.py
dubhub/test_schema.py
dubhub/utils.py
dubhub/version.py
dubhub/commands/__init__.py
dubhub/commands/base.py
dubhub/commands/baseguard.py
dubhub/commands/clone.py
dubhub/commands/dub.py
dubhub/commands/init.py
dubhub/commands/mcp.py
dubhub/commands/mcp_server.py
dubhub/commands/schema.py
dubhub-0.9.0.dist-info/licenses/LICENSE
dubhub-0.9.0.dist-info/METADATA
dubhub-0.9.0.dist-info/WHEEL
dubhub-0.9.0.dist-info/entry_points.txt
dubhub-0.9.0.dist-info/top_level.txt
dubhub-0.9.0.dist-info/RECORD
