Metadata-Version: 2.4
Name: dubhub
Version: 0.9.0
Summary: Dubhub CLI
Home-page: https://dubhub.io
License: BSD 2-Clause License
License-File: LICENSE
Requires-Dist: requests
Requires-Dist: importlib-metadata; python_version < "3.8"
Requires-Dist: sentry-sdk
Requires-Dist: psycopg
Requires-Dist: httpx
Requires-Dist: mcp
Dynamic: license-file
